Metadata-Version: 1.1
Name: django-url-namespaces
Version: 0.1.0
Summary: Declarative class-based datastructures, for simple and flexible URLConfs in Django.
Home-page: http://github.com/fish2000/django-url-namespaces/
Author: Alexander Bohn
Author-email: fish2000@gmail.com
License: MIT
Download-URL: http://github.com/fish2000/django-url-namespaces/zipball/master
Keywords: python django url urlconf config datastructures syntax
Platform: any
Classifier: Development Status :: 5 - Production/Stable
Classifier: License :: OSI Approved :: MIT License
Classifier: Operating System :: MacOS
Classifier: Operating System :: Microsoft :: Windows
Classifier: Operating System :: OS Independent
Classifier: Operating System :: POSIX
Classifier: Operating System :: Unix
Classifier: Programming Language :: Python :: 2.6
